<?xml version="1.0" encoding="UTF-8" ?>
<!DOCTYPE mapper
        PUBLIC "-//mybatis.org//DTD Mapper 3.0//EN"
        "https://mybatis.org/dtd/mybatis-3-mapper.dtd">
<mapper namespace="com.andrew.smartielts.listening.mapper.ListeningMaterialMapper">

    <resultMap id="ListeningMaterialResultMap" type="com.andrew.smartielts.listening.domain.pojo.ListeningMaterial">
        <id column="id" property="id"/>
        <result column="test_id" property="testId"/>
        <result column="part_group_id" property="partGroupId"/>
        <result column="title" property="title"/>
        <result column="audio_url" property="audioUrl"/>
        <result column="audio_object_key" property="audioObjectKey"/>
        <result column="transcript_text" property="transcriptText"/>
        <result column="display_order" property="displayOrder"/>
        <result column="is_deleted" property="isDeleted"/>
    </resultMap>

    <sql id="Base_Column_List">
        id, test_id, part_group_id, title, audio_url, audio_object_key,
        transcript_text, display_order, is_deleted
    </sql>

    <insert id="insertListeningMaterial"
            parameterType="com.andrew.smartielts.listening.domain.pojo.ListeningMaterial"
            useGeneratedKeys="true" keyProperty="id" keyColumn="id">
        insert into listening_material (
        test_id, part_group_id, title, audio_url, audio_object_key,
        transcript_text, display_order, is_deleted
        ) values (
        #{testId}, #{partGroupId}, #{title}, #{audioUrl}, #{audioObjectKey},
        #{transcriptText}, #{displayOrder}, 0
        )
    </insert>

    <select id="findActiveById" resultMap="ListeningMaterialResultMap">
        select <include refid="Base_Column_List"/>
        from listening_material
        where id = #{id}
        and is_deleted = 0
    </select>

    <select id="findAnyById" resultMap="ListeningMaterialResultMap">
        select <include refid="Base_Column_List"/>
        from listening_material
        where id = #{id}
    </select>

    <select id="findActiveByTestId" resultMap="ListeningMaterialResultMap">
        select <include refid="Base_Column_List"/>
        from listening_material
        where test_id = #{testId}
        and is_deleted = 0
        order by display_order asc, id asc
    </select>

    <select id="findAnyByTestId" resultMap="ListeningMaterialResultMap">
        select <include refid="Base_Column_List"/>
        from listening_material
        where test_id = #{testId}
        order by display_order asc, id asc
    </select>

    <select id="findActiveByPartGroupId" resultMap="ListeningMaterialResultMap">
        select <include refid="Base_Column_List"/>
        from listening_material
        where part_group_id = #{partGroupId}
        and is_deleted = 0
        order by display_order asc, id asc
    </select>

    <select id="findAnyByPartGroupId" resultMap="ListeningMaterialResultMap">
        select <include refid="Base_Column_List"/>
        from listening_material
        where part_group_id = #{partGroupId}
        order by display_order asc, id asc
    </select>

    <update id="updateListeningMaterial"
            parameterType="com.andrew.smartielts.listening.domain.pojo.ListeningMaterial">
        update listening_material
        set part_group_id = #{partGroupId},
        title = #{title},
        audio_url = #{audioUrl},
        audio_object_key = #{audioObjectKey},
        transcript_text = #{transcriptText},
        display_order = #{displayOrder}
        where id = #{id}
    </update>

    <update id="softDeleteById">
        update listening_material
        set is_deleted = 1
        where id = #{id}
        and is_deleted = 0
    </update>

    <update id="softDeleteByTestId">
        update listening_material
        set is_deleted = 1
        where test_id = #{testId}
        and is_deleted = 0
    </update>

    <update id="softDeleteByPartGroupId">
        update listening_material
        set is_deleted = 1
        where part_group_id = #{partGroupId}
        and is_deleted = 0
    </update>

    <update id="restoreById">
        update listening_material
        set is_deleted = 0
        where id = #{id}
        and is_deleted = 1
    </update>

    <update id="restoreByTestId">
        update listening_material
        set is_deleted = 0
        where test_id = #{testId}
        and is_deleted = 1
    </update>

    <update id="restoreByPartGroupId">
        update listening_material
        set is_deleted = 0
        where part_group_id = #{partGroupId}
        and is_deleted = 1
    </update>
</mapper>